{
  "snapshotId": "a6082a05-9bfb-4c39-ba6e-099bdb4ef1eb",
  "twitterId": "1738505355905101824",
  "scannedAt": "2026-05-07T10:53:38.273Z",
  "fields": {
    "username": "haj_sadegh_8",
    "displayName": "🎒فرمانده☫",
    "profileImageUrl": "https://pbs.twimg.com/profile_images/2045213797804023808/17VNhpU2_normal.jpg",
    "profileBannerUrl": "https://pbs.twimg.com/profile_banners/1738505355905101824/1774607608",
    "bio": "تا آخرین نفر ، تا آخرین نفس",
    "selfLocation": "جمهوری اسلامی ایران",
    "accountBasedIn": "Iran",
    "connectedVia": "Iran Android App",
    "locatedCountryAccurate": true,
    "verified": false
  },
  "rawPayload": {
    "about_account_query_raw": {
      "data": {
        "user_result_by_screen_name": {
          "id": "VXNlclJlc3VsdHM6MTczODUwNTM1NTkwNTEwMTgyNA==",
          "result": {
            "id": "VXNlcjoxNzM4NTA1MzU1OTA1MTAxODI0",
            "core": {
              "name": "🎒فرمانده☫",
              "created_at": "Sat Dec 23 10:23:06 +0000 2023",
              "screen_name": "haj_sadegh_8"
            },
            "avatar": {
              "image_url": "https://pbs.twimg.com/profile_images/2045213797804023808/17VNhpU2_normal.jpg"
            },
            "privacy": {
              "protected": false
            },
            "rest_id": "1738505355905101824",
            "__typename": "User",
            "verification": {
              "verified": false
            },
            "about_profile": {
              "source": "Iran Android App",
              "learn_more_url": "https://help.twitter.com/rules-and-policies/profile-labels",
              "account_based_in": "Iran",
              "username_changes": {
                "count": "3",
                "last_changed_at_msec": "1721827216778"
              },
              "location_accurate": true,
              "created_country_accurate": true
            },
            "is_blue_verified": false,
            "verification_info": {
              "id": "VXNlclZlcmlmaWNhdGlvbkluZm86MTczODUwNTM1NTkwNTEwMTgyNA==",
              "is_identity_verified": false
            },
            "profile_image_shape": "Circle",
            "affiliates_highlighted_label": {},
            "identity_profile_labels_highlighted_label": {}
          }
        }
      }
    },
    "user_by_screen_name_raw": {
      "data": {
        "user": {
          "result": {
            "id": "VXNlcjoxNzM4NTA1MzU1OTA1MTAxODI0",
            "core": {
              "name": "🎒فرمانده☫",
              "created_at": "Sat Dec 23 10:23:06 +0000 2023",
              "screen_name": "haj_sadegh_8"
            },
            "avatar": {
              "image_url": "https://pbs.twimg.com/profile_images/2045213797804023808/17VNhpU2_normal.jpg"
            },
            "legacy": {
              "url": "",
              "entities": {
                "description": {}
              },
              "time_zone": "",
              "utc_offset": 0,
              "description": "تا آخرین نفر ، تا آخرین نفس",
              "media_count": 221,
              "listed_count": 2,
              "friends_count": 2376,
              "is_translator": false,
              "notifications": false,
              "want_retweets": false,
              "statuses_count": 2741,
              "withheld_scope": "",
              "default_profile": true,
              "followers_count": 1675,
              "translator_type": "none",
              "favourites_count": 3738,
              "possibly_sensitive": false,
              "profile_banner_url": "https://pbs.twimg.com/profile_banners/1738505355905101824/1774607608",
              "follow_request_sent": false,
              "fast_followers_count": 0,
              "has_custom_timelines": false,
              "withheld_description": "",
              "default_profile_image": false,
              "normal_followers_count": 1675,
              "needs_phone_verification": false,
              "profile_interstitial_type": ""
            },
            "privacy": {
              "protected": false
            },
            "rest_id": "1738505355905101824",
            "location": {
              "location": "جمهوری اسلامی ایران"
            },
            "__typename": "User",
            "profile_bio": {
              "description": "تا آخرین نفر ، تا آخرین نفس"
            },
            "professional": {
              "rest_id": "1738644838537425298",
              "category": [],
              "professional_type": "Creator"
            },
            "verification": {
              "verified": false
            },
            "dm_permissions": {
              "can_dm": false
            },
            "highlights_info": {
              "highlighted_tweets": "0",
              "can_highlight_tweets": false
            },
            "super_following": false,
            "business_account": {},
            "is_blue_verified": false,
            "media_permissions": {
              "can_media_tag": true
            },
            "super_followed_by": false,
            "verification_info": {
              "is_identity_verified": false
            },
            "follow_request_sent": false,
            "profile_image_shape": "Circle",
            "has_graduated_access": true,
            "profile_sort_enabled": true,
            "super_follow_eligible": false,
            "user_seed_tweet_count": 0,
            "is_profile_translatable": false,
            "legacy_extended_profile": {},
            "premium_gifting_eligible": true,
            "creator_subscriptions_count": 0,
            "parody_commentary_fan_label": "None",
            "affiliates_highlighted_label": {},
            "profile_description_language": "fa",
            "has_hidden_subscriptions_on_profile": false,
            "grok_translated_bio_with_availability": {
              "is_available": false
            }
          }
        }
      }
    }
  }
}