{
  "snapshotId": "134109d9-befc-4d36-b59b-b0f54197a35b",
  "twitterId": "837237062935973889",
  "scannedAt": "2026-07-04T04:11:04.953Z",
  "fields": {
    "username": "morteza_pn",
    "displayName": "مرتضی پناهیان ☫",
    "profileImageUrl": "https://pbs.twimg.com/profile_images/2047286208045219840/Pa1MRNuU_normal.jpg",
    "profileBannerUrl": "https://pbs.twimg.com/profile_banners/837237062935973889/1664859961",
    "bio": "طلبه و معلم\n💍",
    "selfLocation": "Islamic Republic of Iran",
    "accountBasedIn": "Iran",
    "connectedVia": "Iran Android App",
    "locatedCountryAccurate": true,
    "verified": false
  },
  "rawPayload": {
    "user_by_screen_name_raw": {
      "data": {
        "user": {
          "result": {
            "__typename": "User",
            "affiliates_highlighted_label": {},
            "avatar": {
              "image_url": "https://pbs.twimg.com/profile_images/2047286208045219840/Pa1MRNuU_normal.jpg"
            },
            "business_account": {},
            "core": {
              "created_at": "Thu Mar 02 09:44:05 +0000 2017",
              "name": "مرتضی پناهیان ☫",
              "screen_name": "morteza_pn"
            },
            "creator_subscriptions_count": 0,
            "dm_permissions": {
              "can_dm": false
            },
            "follow_request_sent": false,
            "grok_translated_bio_with_availability": {
              "is_available": false
            },
            "has_graduated_access": true,
            "has_hidden_subscriptions_on_profile": false,
            "highlights_info": {
              "can_highlight_tweets": false,
              "highlighted_tweets": "0"
            },
            "id": "VXNlcjo4MzcyMzcwNjI5MzU5NzM4ODk=",
            "is_blue_verified": false,
            "is_profile_translatable": true,
            "legacy": {
              "default_profile": true,
              "default_profile_image": false,
              "description": "طلبه و معلم\n💍",
              "entities": {
                "description": {},
                "url": {
                  "urls": [
                    {
                      "display_url": "instagram.com/panahian.morte…",
                      "expanded_url": "http://instagram.com/panahian.morteza",
                      "indices": [
                        0,
                        23
                      ],
                      "url": "https://t.co/JMKFHpEmKt"
                    }
                  ]
                }
              },
              "fast_followers_count": 0,
              "favourites_count": 142706,
              "follow_request_sent": false,
              "followers_count": 8311,
              "friends_count": 3505,
              "has_custom_timelines": true,
              "is_translator": false,
              "listed_count": 32,
              "media_count": 658,
              "needs_phone_verification": false,
              "normal_followers_count": 8311,
              "notifications": false,
              "pinned_tweet_ids_str": [
                "1586814947199180807"
              ],
              "possibly_sensitive": false,
              "profile_banner_url": "https://pbs.twimg.com/profile_banners/837237062935973889/1664859961",
              "profile_interstitial_type": "",
              "statuses_count": 14569,
              "time_zone": "",
              "translator_type": "none",
              "url": "https://t.co/JMKFHpEmKt",
              "utc_offset": 0,
              "want_retweets": false,
              "withheld_description": "",
              "withheld_scope": ""
            },
            "legacy_extended_profile": {
              "birthdate": {
                "day": 12,
                "month": 2,
                "visibility": "Public",
                "year_visibility": "Self"
              }
            },
            "location": {
              "location": "Islamic Republic of Iran"
            },
            "media_permissions": {
              "can_media_tag": true
            },
            "parody_commentary_fan_label": "None",
            "premium_gifting_eligible": true,
            "privacy": {
              "protected": false
            },
            "professional": {
              "category": [
                {
                  "icon_name": "IconBriefcaseStroke",
                  "id": 164,
                  "name": "Religious School"
                }
              ],
              "professional_type": "Creator",
              "rest_id": "1603665017756319745"
            },
            "profile_bio": {
              "description": "طلبه و معلم\n💍"
            },
            "profile_description_language": "ar",
            "profile_image_shape": "Circle",
            "profile_sort_enabled": true,
            "rest_id": "837237062935973889",
            "super_follow_eligible": false,
            "super_followed_by": false,
            "super_following": false,
            "user_seed_tweet_count": 0,
            "verification": {
              "verified": false
            },
            "verification_info": {
              "is_identity_verified": false
            }
          }
        }
      }
    },
    "about_account_query_raw": {
      "data": {
        "user_result_by_screen_name": {
          "id": "VXNlclJlc3VsdHM6ODM3MjM3MDYyOTM1OTczODg5",
          "result": {
            "__typename": "User",
            "about_profile": {
              "account_based_in": "Iran",
              "created_country_accurate": true,
              "learn_more_url": "https://help.twitter.com/rules-and-policies/profile-labels",
              "location_accurate": true,
              "source": "Iran Android App",
              "username_changes": {
                "count": "1",
                "last_changed_at_msec": "1488447892477"
              }
            },
            "affiliates_highlighted_label": {},
            "avatar": {
              "image_url": "https://pbs.twimg.com/profile_images/2047286208045219840/Pa1MRNuU_normal.jpg"
            },
            "core": {
              "created_at": "Thu Mar 02 09:44:05 +0000 2017",
              "name": "مرتضی پناهیان ☫",
              "screen_name": "morteza_pn"
            },
            "id": "VXNlcjo4MzcyMzcwNjI5MzU5NzM4ODk=",
            "identity_profile_labels_highlighted_label": {},
            "is_blue_verified": false,
            "privacy": {
              "protected": false
            },
            "profile_image_shape": "Circle",
            "rest_id": "837237062935973889",
            "verification": {
              "verified": false
            },
            "verification_info": {
              "id": "VXNlclZlcmlmaWNhdGlvbkluZm86ODM3MjM3MDYyOTM1OTczODg5",
              "is_identity_verified": false
            }
          }
        }
      }
    }
  }
}