{
  "snapshotId": "b75e335d-2266-4e7e-ac0a-6896c8dc91e1",
  "twitterId": "1815733003118837760",
  "scannedAt": "2026-06-27T04:27:13.707Z",
  "fields": {
    "username": "mahboobh593325",
    "displayName": "خانم صولتی",
    "profileImageUrl": "https://pbs.twimg.com/profile_images/1815735341455667201/bedEIFw2_normal.jpg",
    "profileBannerUrl": "https://pbs.twimg.com/profile_banners/1815733003118837760/1728920464",
    "bio": "کارشناس شیمی|عاشق طبیعت|پیرو راه حسین(ع)",
    "selfLocation": "شهرستان درگز ",
    "accountBasedIn": "Iran",
    "connectedVia": "Iran Android App",
    "locatedCountryAccurate": true,
    "verified": false
  },
  "rawPayload": {
    "user_by_screen_name_raw": {
      "data": {
        "user": {
          "result": {
            "__typename": "User",
            "affiliates_highlighted_label": {},
            "avatar": {
              "image_url": "https://pbs.twimg.com/profile_images/1815735341455667201/bedEIFw2_normal.jpg"
            },
            "business_account": {},
            "core": {
              "created_at": "Tue Jul 23 12:58:27 +0000 2024",
              "name": "خانم صولتی",
              "screen_name": "mahboobh593325"
            },
            "creator_subscriptions_count": 0,
            "dm_permissions": {
              "can_dm": true
            },
            "follow_request_sent": false,
            "grok_translated_bio_with_availability": {
              "is_available": false
            },
            "has_graduated_access": true,
            "has_hidden_subscriptions_on_profile": false,
            "highlights_info": {
              "can_highlight_tweets": false,
              "highlighted_tweets": "0"
            },
            "id": "VXNlcjoxODE1NzMzMDAzMTE4ODM3NzYw",
            "is_blue_verified": false,
            "is_profile_translatable": true,
            "legacy": {
              "default_profile": true,
              "default_profile_image": false,
              "description": "کارشناس شیمی|عاشق طبیعت|پیرو راه حسین(ع)",
              "entities": {
                "description": {}
              },
              "fast_followers_count": 0,
              "favourites_count": 2286,
              "follow_request_sent": false,
              "followers_count": 183,
              "friends_count": 366,
              "has_custom_timelines": false,
              "is_translator": false,
              "listed_count": 0,
              "media_count": 282,
              "needs_phone_verification": false,
              "normal_followers_count": 183,
              "notifications": false,
              "possibly_sensitive": true,
              "profile_banner_url": "https://pbs.twimg.com/profile_banners/1815733003118837760/1728920464",
              "profile_interstitial_type": "",
              "statuses_count": 2429,
              "time_zone": "",
              "translator_type": "none",
              "url": "",
              "utc_offset": 0,
              "want_retweets": false,
              "withheld_description": "",
              "withheld_scope": ""
            },
            "legacy_extended_profile": {},
            "location": {
              "location": "شهرستان درگز "
            },
            "media_permissions": {
              "can_media_tag": false
            },
            "parody_commentary_fan_label": "None",
            "premium_gifting_eligible": true,
            "privacy": {
              "protected": false
            },
            "profile_bio": {
              "description": "کارشناس شیمی|عاشق طبیعت|پیرو راه حسین(ع)"
            },
            "profile_description_language": "fa",
            "profile_image_shape": "Circle",
            "profile_sort_enabled": false,
            "rest_id": "1815733003118837760",
            "super_follow_eligible": false,
            "super_followed_by": false,
            "super_following": false,
            "user_seed_tweet_count": 0,
            "verification": {
              "verified": false
            },
            "verification_info": {
              "is_identity_verified": false
            }
          }
        }
      }
    },
    "about_account_query_raw": {
      "data": {
        "user_result_by_screen_name": {
          "id": "VXNlclJlc3VsdHM6MTgxNTczMzAwMzExODgzNzc2MA==",
          "result": {
            "__typename": "User",
            "about_profile": {
              "account_based_in": "Iran",
              "created_country_accurate": true,
              "learn_more_url": "https://help.twitter.com/rules-and-policies/profile-labels",
              "location_accurate": true,
              "source": "Iran Android App",
              "username_changes": {
                "count": "0"
              }
            },
            "affiliates_highlighted_label": {},
            "avatar": {
              "image_url": "https://pbs.twimg.com/profile_images/1815735341455667201/bedEIFw2_normal.jpg"
            },
            "core": {
              "created_at": "Tue Jul 23 12:58:27 +0000 2024",
              "name": "خانم صولتی",
              "screen_name": "mahboobh593325"
            },
            "id": "VXNlcjoxODE1NzMzMDAzMTE4ODM3NzYw",
            "identity_profile_labels_highlighted_label": {},
            "is_blue_verified": false,
            "privacy": {
              "protected": false
            },
            "profile_image_shape": "Circle",
            "rest_id": "1815733003118837760",
            "verification": {
              "verified": false
            },
            "verification_info": {
              "id": "VXNlclZlcmlmaWNhdGlvbkluZm86MTgxNTczMzAwMzExODgzNzc2MA==",
              "is_identity_verified": false
            }
          }
        }
      }
    }
  }
}