{
  "snapshotId": "4c7b99da-16dd-4428-ad54-3e7159fafbd8",
  "twitterId": "1661356051952705539",
  "scannedAt": "2026-06-21T09:09:45.715Z",
  "fields": {
    "username": "yasi_313_razagh",
    "displayName": "Nazanin_R313",
    "profileImageUrl": "https://pbs.twimg.com/profile_images/2057808290101276673/nPiyokBf_normal.jpg",
    "profileBannerUrl": "https://pbs.twimg.com/profile_banners/1661356051952705539/1779454738",
    "bio": "عاشق منتظر|| پرستار || رفیقم کتاب|| معلمم خواهرم||\nعاشق🍗🥩🌮🍕🥧",
    "selfLocation": "آذربایجان شرقی ",
    "accountBasedIn": "Iran",
    "connectedVia": "Iran Android App",
    "locatedCountryAccurate": true,
    "verified": false
  },
  "rawPayload": {
    "about_account_query_raw": {
      "data": {
        "user_result_by_screen_name": {
          "id": "VXNlclJlc3VsdHM6MTY2MTM1NjA1MTk1MjcwNTUzOQ==",
          "result": {
            "id": "VXNlcjoxNjYxMzU2MDUxOTUyNzA1NTM5",
            "core": {
              "name": "Nazanin_R313",
              "created_at": "Wed May 24 12:59:32 +0000 2023",
              "screen_name": "yasi_313_razagh"
            },
            "avatar": {
              "image_url": "https://pbs.twimg.com/profile_images/2057808290101276673/nPiyokBf_normal.jpg"
            },
            "privacy": {
              "protected": false
            },
            "rest_id": "1661356051952705539",
            "__typename": "User",
            "verification": {
              "verified": false
            },
            "about_profile": {
              "source": "Iran Android App",
              "learn_more_url": "https://help.twitter.com/rules-and-policies/profile-labels",
              "account_based_in": "Iran",
              "username_changes": {
                "count": "8",
                "last_changed_at_msec": "1774968335898"
              },
              "location_accurate": true,
              "created_country_accurate": true
            },
            "is_blue_verified": false,
            "verification_info": {
              "id": "VXNlclZlcmlmaWNhdGlvbkluZm86MTY2MTM1NjA1MTk1MjcwNTUzOQ==",
              "is_identity_verified": false
            },
            "profile_image_shape": "Circle",
            "affiliates_highlighted_label": {},
            "identity_profile_labels_highlighted_label": {}
          }
        }
      }
    },
    "user_by_screen_name_raw": {
      "data": {
        "user": {
          "result": {
            "id": "VXNlcjoxNjYxMzU2MDUxOTUyNzA1NTM5",
            "core": {
              "name": "Nazanin_R313",
              "created_at": "Wed May 24 12:59:32 +0000 2023",
              "screen_name": "yasi_313_razagh"
            },
            "avatar": {
              "image_url": "https://pbs.twimg.com/profile_images/2057808290101276673/nPiyokBf_normal.jpg"
            },
            "legacy": {
              "url": "",
              "entities": {
                "description": {}
              },
              "time_zone": "",
              "utc_offset": 0,
              "description": "عاشق منتظر|| پرستار || رفیقم کتاب|| معلمم خواهرم||\nعاشق🍗🥩🌮🍕🥧",
              "media_count": 167,
              "listed_count": 2,
              "friends_count": 1727,
              "is_translator": false,
              "notifications": false,
              "want_retweets": false,
              "statuses_count": 5067,
              "withheld_scope": "",
              "default_profile": true,
              "followers_count": 1684,
              "translator_type": "none",
              "favourites_count": 9832,
              "possibly_sensitive": false,
              "profile_banner_url": "https://pbs.twimg.com/profile_banners/1661356051952705539/1779454738",
              "follow_request_sent": false,
              "fast_followers_count": 0,
              "has_custom_timelines": false,
              "withheld_description": "",
              "default_profile_image": false,
              "normal_followers_count": 1684,
              "needs_phone_verification": false,
              "profile_interstitial_type": ""
            },
            "privacy": {
              "protected": false
            },
            "rest_id": "1661356051952705539",
            "location": {
              "location": "آذربایجان شرقی "
            },
            "__typename": "User",
            "profile_bio": {
              "description": "عاشق منتظر|| پرستار || رفیقم کتاب|| معلمم خواهرم||\nعاشق🍗🥩🌮🍕🥧"
            },
            "professional": {
              "rest_id": "1667423869743800320",
              "category": [],
              "professional_type": "Creator"
            },
            "verification": {
              "verified": false
            },
            "dm_permissions": {
              "can_dm": false
            },
            "highlights_info": {
              "highlighted_tweets": "0",
              "can_highlight_tweets": false
            },
            "super_following": false,
            "business_account": {},
            "is_blue_verified": false,
            "media_permissions": {
              "can_media_tag": true
            },
            "super_followed_by": false,
            "verification_info": {
              "is_identity_verified": false
            },
            "follow_request_sent": false,
            "profile_image_shape": "Circle",
            "has_graduated_access": true,
            "profile_sort_enabled": false,
            "super_follow_eligible": false,
            "user_seed_tweet_count": 0,
            "is_profile_translatable": false,
            "legacy_extended_profile": {},
            "premium_gifting_eligible": true,
            "creator_subscriptions_count": 0,
            "parody_commentary_fan_label": "None",
            "affiliates_highlighted_label": {},
            "profile_description_language": "fa",
            "has_hidden_subscriptions_on_profile": false,
            "grok_translated_bio_with_availability": {
              "is_available": false
            }
          }
        }
      }
    }
  }
}