{
  "snapshotId": "e24f21f5-4612-4029-b536-f7f604ca6b98",
  "twitterId": "1215293826467688449",
  "scannedAt": "2026-07-23T03:08:07.694Z",
  "fields": {
    "username": "Anil3928",
    "displayName": "آنیل",
    "profileImageUrl": "https://pbs.twimg.com/profile_images/1815628579163496448/GguV1bZu_normal.jpg",
    "profileBannerUrl": "https://pbs.twimg.com/profile_banners/1215293826467688449/1744978134",
    "bio": "استاد درس فوریتهای پزشکی ،ارشدپرستاری ،اهل طنزم،تخصصی بحث کردن رودوست دارم.عاشق  ایران و انقلابم ،مشتاق نوشتنم،عضو مدرسه نویسندگی تصنیف رسانه",
    "selfLocation": "",
    "accountBasedIn": "Iran",
    "connectedVia": "Iran Android App",
    "locatedCountryAccurate": true,
    "verified": false
  },
  "rawPayload": {
    "user_by_screen_name_raw": {
      "data": {
        "user": {
          "result": {
            "__typename": "User",
            "affiliates_highlighted_label": {},
            "avatar": {
              "image_url": "https://pbs.twimg.com/profile_images/1815628579163496448/GguV1bZu_normal.jpg"
            },
            "business_account": {},
            "core": {
              "created_at": "Thu Jan 09 15:26:56 +0000 2020",
              "name": "آنیل",
              "screen_name": "Anil3928"
            },
            "creator_subscriptions_count": 0,
            "dm_permissions": {
              "can_dm": true
            },
            "follow_request_sent": false,
            "grok_translated_bio_with_availability": {
              "is_available": false
            },
            "has_graduated_access": true,
            "has_hidden_subscriptions_on_profile": false,
            "highlights_info": {
              "can_highlight_tweets": false,
              "highlighted_tweets": "0"
            },
            "id": "VXNlcjoxMjE1MjkzODI2NDY3Njg4NDQ5",
            "is_blue_verified": false,
            "is_profile_translatable": true,
            "legacy": {
              "default_profile": true,
              "default_profile_image": false,
              "description": "استاد درس فوریتهای پزشکی ،ارشدپرستاری ،اهل طنزم،تخصصی بحث کردن رودوست دارم.عاشق  ایران و انقلابم ،مشتاق نوشتنم،عضو مدرسه نویسندگی تصنیف رسانه",
              "entities": {
                "description": {}
              },
              "fast_followers_count": 0,
              "favourites_count": 16768,
              "follow_request_sent": false,
              "followers_count": 3236,
              "friends_count": 3540,
              "has_custom_timelines": false,
              "is_translator": false,
              "listed_count": 2,
              "media_count": 815,
              "needs_phone_verification": false,
              "normal_followers_count": 3236,
              "notifications": false,
              "pinned_tweet_ids_str": [
                "1986806020023136303"
              ],
              "possibly_sensitive": false,
              "profile_banner_url": "https://pbs.twimg.com/profile_banners/1215293826467688449/1744978134",
              "profile_interstitial_type": "",
              "statuses_count": 3919,
              "time_zone": "",
              "translator_type": "none",
              "url": "",
              "utc_offset": 0,
              "want_retweets": false,
              "withheld_description": "",
              "withheld_scope": ""
            },
            "legacy_extended_profile": {},
            "location": {
              "location": ""
            },
            "media_permissions": {
              "can_media_tag": true
            },
            "parody_commentary_fan_label": "None",
            "premium_gifting_eligible": true,
            "privacy": {
              "protected": false
            },
            "profile_bio": {
              "description": "استاد درس فوریتهای پزشکی ،ارشدپرستاری ،اهل طنزم،تخصصی بحث کردن رودوست دارم.عاشق  ایران و انقلابم ،مشتاق نوشتنم،عضو مدرسه نویسندگی تصنیف رسانه"
            },
            "profile_description_language": "fa",
            "profile_image_shape": "Circle",
            "profile_sort_enabled": true,
            "rest_id": "1215293826467688449",
            "super_follow_eligible": false,
            "super_followed_by": false,
            "super_following": false,
            "user_seed_tweet_count": 0,
            "verification": {
              "verified": false
            },
            "verification_info": {
              "is_identity_verified": false
            }
          }
        }
      }
    },
    "about_account_query_raw": {
      "data": {
        "user_result_by_screen_name": {
          "id": "VXNlclJlc3VsdHM6MTIxNTI5MzgyNjQ2NzY4ODQ0OQ==",
          "result": {
            "__typename": "User",
            "about_profile": {
              "account_based_in": "Iran",
              "created_country_accurate": true,
              "learn_more_url": "https://help.twitter.com/rules-and-policies/profile-labels",
              "location_accurate": true,
              "source": "Iran Android App",
              "username_changes": {
                "count": "5",
                "last_changed_at_msec": "1593112514315"
              }
            },
            "affiliates_highlighted_label": {},
            "avatar": {
              "image_url": "https://pbs.twimg.com/profile_images/1815628579163496448/GguV1bZu_normal.jpg"
            },
            "core": {
              "created_at": "Thu Jan 09 15:26:56 +0000 2020",
              "name": "آنیل",
              "screen_name": "Anil3928"
            },
            "id": "VXNlcjoxMjE1MjkzODI2NDY3Njg4NDQ5",
            "identity_profile_labels_highlighted_label": {},
            "is_blue_verified": false,
            "privacy": {
              "protected": false
            },
            "profile_image_shape": "Circle",
            "rest_id": "1215293826467688449",
            "verification": {
              "verified": false
            },
            "verification_info": {
              "id": "VXNlclZlcmlmaWNhdGlvbkluZm86MTIxNTI5MzgyNjQ2NzY4ODQ0OQ==",
              "is_identity_verified": false
            }
          }
        }
      }
    }
  }
}