{
  "snapshotId": "2bd53d8c-eceb-4899-be5b-7ef9f0088fe7",
  "twitterId": "4262821696",
  "scannedAt": "2026-07-07T08:49:24.211Z",
  "fields": {
    "username": "founder_23",
    "displayName": "بـــــــــــرنامه_نویسیونـــــــــــــــــــــــــ",
    "profileImageUrl": "https://pbs.twimg.com/profile_images/2055337171892961280/I9fzNfUZ_normal.jpg",
    "profileBannerUrl": "https://pbs.twimg.com/profile_banners/4262821696/1777761833",
    "bio": "01001101 01101001 01101100 01100001 01100100",
    "selfLocation": "Tehran",
    "accountBasedIn": "Iran",
    "connectedVia": "United States App Store",
    "locatedCountryAccurate": false,
    "verified": false
  },
  "rawPayload": {
    "user_by_screen_name_raw": {
      "data": {
        "user": {
          "result": {
            "__typename": "User",
            "affiliates_highlighted_label": {},
            "avatar": {
              "image_url": "https://pbs.twimg.com/profile_images/2055337171892961280/I9fzNfUZ_normal.jpg"
            },
            "business_account": {},
            "core": {
              "created_at": "Tue Nov 24 06:23:20 +0000 2015",
              "name": "بـــــــــــرنامه_نویسیونـــــــــــــــــــــــــ",
              "screen_name": "founder_23"
            },
            "creator_subscriptions_count": 0,
            "dm_permissions": {
              "can_dm": false
            },
            "follow_request_sent": false,
            "grok_translated_bio_with_availability": {
              "is_available": false
            },
            "has_graduated_access": true,
            "has_hidden_subscriptions_on_profile": false,
            "highlights_info": {
              "can_highlight_tweets": false,
              "highlighted_tweets": "0"
            },
            "id": "VXNlcjo0MjYyODIxNjk2",
            "is_blue_verified": false,
            "is_profile_translatable": false,
            "legacy": {
              "default_profile": true,
              "default_profile_image": false,
              "description": "01001101 01101001 01101100 01100001 01100100",
              "entities": {
                "description": {}
              },
              "fast_followers_count": 0,
              "favourites_count": 4364,
              "follow_request_sent": false,
              "followers_count": 486,
              "friends_count": 1124,
              "has_custom_timelines": false,
              "is_translator": false,
              "listed_count": 1,
              "media_count": 24,
              "needs_phone_verification": false,
              "normal_followers_count": 486,
              "notifications": false,
              "pinned_tweet_ids_str": [
                "2073705837869117682"
              ],
              "possibly_sensitive": false,
              "profile_banner_url": "https://pbs.twimg.com/profile_banners/4262821696/1777761833",
              "profile_interstitial_type": "",
              "statuses_count": 446,
              "time_zone": "",
              "translator_type": "none",
              "url": "",
              "utc_offset": 0,
              "want_retweets": false,
              "withheld_description": "",
              "withheld_scope": ""
            },
            "legacy_extended_profile": {},
            "location": {
              "location": "Tehran"
            },
            "media_permissions": {
              "can_media_tag": true
            },
            "parody_commentary_fan_label": "None",
            "premium_gifting_eligible": true,
            "privacy": {
              "protected": false
            },
            "professional": {
              "category": [
                {
                  "icon_name": "IconBriefcaseStroke",
                  "id": 508,
                  "name": "Web Design Agency"
                }
              ],
              "professional_type": "Creator",
              "rest_id": "1557398178692988929"
            },
            "profile_bio": {
              "description": "01001101 01101001 01101100 01100001 01100100"
            },
            "profile_image_shape": "Circle",
            "profile_sort_enabled": false,
            "rest_id": "4262821696",
            "super_follow_eligible": false,
            "super_followed_by": false,
            "super_following": false,
            "user_seed_tweet_count": 0,
            "verification": {
              "verified": false
            },
            "verification_info": {
              "is_identity_verified": false
            }
          }
        }
      }
    },
    "about_account_query_raw": {
      "data": {
        "user_result_by_screen_name": {
          "id": "VXNlclJlc3VsdHM6NDI2MjgyMTY5Ng==",
          "result": {
            "__typename": "User",
            "about_profile": {
              "account_based_in": "Iran",
              "created_country_accurate": true,
              "learn_more_url": "https://help.twitter.com/rules-and-policies/profile-labels",
              "location_accurate": false,
              "source": "United States App Store",
              "username_changes": {
                "count": "2",
                "last_changed_at_msec": "1743191995292"
              }
            },
            "affiliates_highlighted_label": {},
            "avatar": {
              "image_url": "https://pbs.twimg.com/profile_images/2055337171892961280/I9fzNfUZ_normal.jpg"
            },
            "core": {
              "created_at": "Tue Nov 24 06:23:20 +0000 2015",
              "name": "بـــــــــــرنامه_نویسیونـــــــــــــــــــــــــ",
              "screen_name": "founder_23"
            },
            "id": "VXNlcjo0MjYyODIxNjk2",
            "identity_profile_labels_highlighted_label": {},
            "is_blue_verified": false,
            "privacy": {
              "protected": false
            },
            "profile_image_shape": "Circle",
            "rest_id": "4262821696",
            "verification": {
              "verified": false
            },
            "verification_info": {
              "id": "VXNlclZlcmlmaWNhdGlvbkluZm86NDI2MjgyMTY5Ng==",
              "is_identity_verified": false
            }
          }
        }
      }
    }
  }
}