{
  "snapshotId": "1038a36f-c4ed-456d-8a8b-029e79a1df21",
  "twitterId": "993788661849354240",
  "scannedAt": "2026-07-04T06:08:08.383Z",
  "fields": {
    "username": "royababaei19",
    "displayName": "رویا بابایی/خبرنگار حوزه معلولان",
    "profileImageUrl": "https://pbs.twimg.com/profile_images/993798791605178368/ZzOx3KEm_normal.jpg",
    "profileBannerUrl": "https://pbs.twimg.com/profile_banners/993788661849354240/1525775069",
    "bio": "/ارشد ارتباطات/خبرنگار حوزه معلولین",
    "selfLocation": "",
    "accountBasedIn": "Iran",
    "connectedVia": "Netherlands Android App",
    "locatedCountryAccurate": true,
    "verified": false
  },
  "rawPayload": {
    "user_by_screen_name_raw": {
      "data": {
        "user": {
          "result": {
            "__typename": "User",
            "affiliates_highlighted_label": {},
            "avatar": {
              "image_url": "https://pbs.twimg.com/profile_images/993798791605178368/ZzOx3KEm_normal.jpg"
            },
            "business_account": {},
            "core": {
              "created_at": "Tue May 08 09:44:15 +0000 2018",
              "name": "رویا بابایی/خبرنگار حوزه معلولان",
              "screen_name": "royababaei19"
            },
            "creator_subscriptions_count": 0,
            "dm_permissions": {
              "can_dm": true
            },
            "follow_request_sent": false,
            "grok_translated_bio_with_availability": {
              "is_available": false
            },
            "has_graduated_access": true,
            "has_hidden_subscriptions_on_profile": false,
            "highlights_info": {
              "can_highlight_tweets": false,
              "highlighted_tweets": "0"
            },
            "id": "VXNlcjo5OTM3ODg2NjE4NDkzNTQyNDA=",
            "is_blue_verified": false,
            "is_profile_translatable": true,
            "legacy": {
              "default_profile": true,
              "default_profile_image": false,
              "description": "/ارشد ارتباطات/خبرنگار حوزه معلولین",
              "entities": {
                "description": {}
              },
              "fast_followers_count": 0,
              "favourites_count": 1304,
              "follow_request_sent": false,
              "followers_count": 1057,
              "friends_count": 708,
              "has_custom_timelines": true,
              "is_translator": false,
              "listed_count": 6,
              "media_count": 152,
              "needs_phone_verification": false,
              "normal_followers_count": 1057,
              "notifications": false,
              "possibly_sensitive": false,
              "profile_banner_url": "https://pbs.twimg.com/profile_banners/993788661849354240/1525775069",
              "profile_interstitial_type": "",
              "statuses_count": 281,
              "time_zone": "",
              "translator_type": "none",
              "url": "",
              "utc_offset": 0,
              "want_retweets": false,
              "withheld_description": "",
              "withheld_scope": ""
            },
            "legacy_extended_profile": {},
            "location": {
              "location": ""
            },
            "media_permissions": {
              "can_media_tag": true
            },
            "parody_commentary_fan_label": "None",
            "premium_gifting_eligible": true,
            "privacy": {
              "protected": false
            },
            "profile_bio": {
              "description": "/ارشد ارتباطات/خبرنگار حوزه معلولین"
            },
            "profile_description_language": "fa",
            "profile_image_shape": "Circle",
            "profile_sort_enabled": true,
            "rest_id": "993788661849354240",
            "super_follow_eligible": false,
            "super_followed_by": false,
            "super_following": false,
            "user_seed_tweet_count": 0,
            "verification": {
              "verified": false
            },
            "verification_info": {
              "is_identity_verified": false
            }
          }
        }
      }
    },
    "about_account_query_raw": {
      "data": {
        "user_result_by_screen_name": {
          "id": "VXNlclJlc3VsdHM6OTkzNzg4NjYxODQ5MzU0MjQw",
          "result": {
            "__typename": "User",
            "about_profile": {
              "account_based_in": "Iran",
              "created_country_accurate": true,
              "learn_more_url": "https://help.twitter.com/rules-and-policies/profile-labels",
              "location_accurate": true,
              "source": "Netherlands Android App",
              "username_changes": {
                "count": "1",
                "last_changed_at_msec": "1525773212084"
              }
            },
            "affiliates_highlighted_label": {},
            "avatar": {
              "image_url": "https://pbs.twimg.com/profile_images/993798791605178368/ZzOx3KEm_normal.jpg"
            },
            "core": {
              "created_at": "Tue May 08 09:44:15 +0000 2018",
              "name": "رویا بابایی/خبرنگار حوزه معلولان",
              "screen_name": "royababaei19"
            },
            "id": "VXNlcjo5OTM3ODg2NjE4NDkzNTQyNDA=",
            "identity_profile_labels_highlighted_label": {},
            "is_blue_verified": false,
            "privacy": {
              "protected": false
            },
            "profile_image_shape": "Circle",
            "rest_id": "993788661849354240",
            "verification": {
              "verified": false
            },
            "verification_info": {
              "id": "VXNlclZlcmlmaWNhdGlvbkluZm86OTkzNzg4NjYxODQ5MzU0MjQw",
              "is_identity_verified": false
            }
          }
        }
      }
    }
  }
}