{
  "snapshotId": "97b72eea-1ddf-412a-af65-6dc29666ed1a",
  "twitterId": "876549195339005952",
  "scannedAt": "2026-06-16T05:03:01.438Z",
  "fields": {
    "username": "hamidrahbarifar",
    "displayName": "حميد رهبرى فر",
    "profileImageUrl": "https://pbs.twimg.com/profile_images/1907641982505095168/JGxa4-6a_normal.jpg",
    "profileBannerUrl": "https://pbs.twimg.com/profile_banners/876549195339005952/1734957760",
    "bio": "مرنج و مرنجان",
    "selfLocation": "iran",
    "accountBasedIn": "West Asia",
    "connectedVia": "North America App Store",
    "locatedCountryAccurate": true,
    "verified": false
  },
  "rawPayload": {
    "about_account_query_raw": {
      "data": {
        "user_result_by_screen_name": {
          "id": "VXNlclJlc3VsdHM6ODc2NTQ5MTk1MzM5MDA1OTUy",
          "result": {
            "id": "VXNlcjo4NzY1NDkxOTUzMzkwMDU5NTI=",
            "core": {
              "name": "حميد رهبرى فر",
              "created_at": "Sun Jun 18 21:16:28 +0000 2017",
              "screen_name": "hamidrahbarifar"
            },
            "avatar": {
              "image_url": "https://pbs.twimg.com/profile_images/1907641982505095168/JGxa4-6a_normal.jpg"
            },
            "privacy": {
              "protected": false
            },
            "rest_id": "876549195339005952",
            "__typename": "User",
            "verification": {
              "verified": false
            },
            "about_profile": {
              "source": "North America App Store",
              "learn_more_url": "https://help.twitter.com/rules-and-policies/profile-labels",
              "account_based_in": "West Asia",
              "username_changes": {
                "count": "1",
                "last_changed_at_msec": "1497820735435"
              },
              "location_accurate": true,
              "created_country_accurate": true
            },
            "is_blue_verified": false,
            "verification_info": {
              "id": "VXNlclZlcmlmaWNhdGlvbkluZm86ODc2NTQ5MTk1MzM5MDA1OTUy",
              "is_identity_verified": false
            },
            "profile_image_shape": "Circle",
            "affiliates_highlighted_label": {},
            "identity_profile_labels_highlighted_label": {}
          }
        }
      }
    },
    "user_by_screen_name_raw": {
      "data": {
        "user": {
          "result": {
            "id": "VXNlcjo4NzY1NDkxOTUzMzkwMDU5NTI=",
            "core": {
              "name": "حميد رهبرى فر",
              "created_at": "Sun Jun 18 21:16:28 +0000 2017",
              "screen_name": "hamidrahbarifar"
            },
            "avatar": {
              "image_url": "https://pbs.twimg.com/profile_images/1907641982505095168/JGxa4-6a_normal.jpg"
            },
            "legacy": {
              "url": "",
              "entities": {
                "description": {}
              },
              "time_zone": "",
              "utc_offset": 0,
              "description": "مرنج و مرنجان",
              "media_count": 34,
              "listed_count": 0,
              "friends_count": 393,
              "is_translator": false,
              "notifications": false,
              "want_retweets": false,
              "statuses_count": 815,
              "withheld_scope": "",
              "default_profile": true,
              "followers_count": 318,
              "translator_type": "none",
              "favourites_count": 1868,
              "possibly_sensitive": false,
              "profile_banner_url": "https://pbs.twimg.com/profile_banners/876549195339005952/1734957760",
              "follow_request_sent": false,
              "fast_followers_count": 0,
              "has_custom_timelines": false,
              "withheld_description": "",
              "default_profile_image": false,
              "normal_followers_count": 318,
              "needs_phone_verification": false,
              "profile_interstitial_type": ""
            },
            "privacy": {
              "protected": false
            },
            "rest_id": "876549195339005952",
            "location": {
              "location": "iran"
            },
            "__typename": "User",
            "profile_bio": {
              "description": "مرنج و مرنجان"
            },
            "verification": {
              "verified": false
            },
            "dm_permissions": {
              "can_dm": false
            },
            "highlights_info": {
              "highlighted_tweets": "0",
              "can_highlight_tweets": false
            },
            "super_following": false,
            "business_account": {},
            "is_blue_verified": false,
            "media_permissions": {
              "can_media_tag": true
            },
            "super_followed_by": false,
            "verification_info": {
              "is_identity_verified": false
            },
            "follow_request_sent": false,
            "profile_image_shape": "Circle",
            "has_graduated_access": true,
            "profile_sort_enabled": false,
            "super_follow_eligible": false,
            "user_seed_tweet_count": 0,
            "is_profile_translatable": true,
            "legacy_extended_profile": {},
            "premium_gifting_eligible": true,
            "creator_subscriptions_count": 0,
            "parody_commentary_fan_label": "None",
            "affiliates_highlighted_label": {},
            "profile_description_language": "ar",
            "has_hidden_subscriptions_on_profile": false,
            "grok_translated_bio_with_availability": {
              "is_available": false
            }
          }
        }
      }
    }
  }
}