{
  "snapshotId": "dc572dbe-0d1b-4d37-a49a-e9c68e96822b",
  "twitterId": "2054825316741259264",
  "scannedAt": "2026-07-08T05:51:04.474Z",
  "fields": {
    "username": "ayran_23131",
    "displayName": "حــ❤ـــب العلـــــــــی(:",
    "profileImageUrl": "https://pbs.twimg.com/profile_images/2054901638557777920/CUkVwcj7_normal.jpg",
    "profileBannerUrl": "https://pbs.twimg.com/profile_banners/2054825316741259264/1778761574",
    "bio": ",\nتو بحث ِ وطن سر به سرمون بزارید ،\n سر به تن ِتون نمیزاریم حالا خود دانید ❤️‍🔥🕶 \n,",
    "selfLocation": "",
    "accountBasedIn": "Iran",
    "connectedVia": "Iran Android App",
    "locatedCountryAccurate": true,
    "verified": false
  },
  "rawPayload": {
    "user_by_screen_name_raw": {
      "data": {
        "user": {
          "result": {
            "__typename": "User",
            "affiliates_highlighted_label": {},
            "avatar": {
              "image_url": "https://pbs.twimg.com/profile_images/2054901638557777920/CUkVwcj7_normal.jpg"
            },
            "business_account": {},
            "core": {
              "created_at": "Thu May 14 07:25:23 +0000 2026",
              "name": "حــ❤ـــب العلـــــــــی(:",
              "screen_name": "ayran_23131"
            },
            "creator_subscriptions_count": 0,
            "dm_permissions": {
              "can_dm": false
            },
            "follow_request_sent": false,
            "grok_translated_bio_with_availability": {
              "is_available": false
            },
            "has_graduated_access": true,
            "has_hidden_subscriptions_on_profile": false,
            "highlights_info": {
              "can_highlight_tweets": false,
              "highlighted_tweets": "0"
            },
            "id": "VXNlcjoyMDU0ODI1MzE2NzQxMjU5MjY0",
            "is_blue_verified": false,
            "is_profile_translatable": true,
            "legacy": {
              "default_profile": true,
              "default_profile_image": false,
              "description": ",\nتو بحث ِ وطن سر به سرمون بزارید ،\n سر به تن ِتون نمیزاریم حالا خود دانید ❤️‍🔥🕶 \n,",
              "entities": {
                "description": {}
              },
              "fast_followers_count": 0,
              "favourites_count": 1579,
              "follow_request_sent": false,
              "followers_count": 261,
              "friends_count": 252,
              "has_custom_timelines": false,
              "is_translator": false,
              "listed_count": 0,
              "media_count": 46,
              "needs_phone_verification": false,
              "normal_followers_count": 261,
              "notifications": false,
              "pinned_tweet_ids_str": [
                "2055925146842706145"
              ],
              "possibly_sensitive": false,
              "profile_banner_url": "https://pbs.twimg.com/profile_banners/2054825316741259264/1778761574",
              "profile_interstitial_type": "",
              "statuses_count": 312,
              "time_zone": "",
              "translator_type": "none",
              "url": "",
              "utc_offset": 0,
              "want_retweets": false,
              "withheld_description": "",
              "withheld_scope": ""
            },
            "legacy_extended_profile": {},
            "location": {
              "location": ""
            },
            "media_permissions": {
              "can_media_tag": true
            },
            "parody_commentary_fan_label": "None",
            "premium_gifting_eligible": true,
            "privacy": {
              "protected": false
            },
            "profile_bio": {
              "description": ",\nتو بحث ِ وطن سر به سرمون بزارید ،\n سر به تن ِتون نمیزاریم حالا خود دانید ❤️‍🔥🕶 \n,"
            },
            "profile_description_language": "fa",
            "profile_image_shape": "Circle",
            "profile_sort_enabled": false,
            "rest_id": "2054825316741259264",
            "super_follow_eligible": false,
            "super_followed_by": false,
            "super_following": false,
            "user_seed_tweet_count": 0,
            "verification": {
              "verified": false
            },
            "verification_info": {
              "is_identity_verified": false
            }
          }
        }
      }
    },
    "about_account_query_raw": {
      "data": {
        "user_result_by_screen_name": {
          "id": "VXNlclJlc3VsdHM6MjA1NDgyNTMxNjc0MTI1OTI2NA==",
          "result": {
            "__typename": "User",
            "about_profile": {
              "account_based_in": "Iran",
              "created_country_accurate": true,
              "learn_more_url": "https://help.twitter.com/rules-and-policies/profile-labels",
              "location_accurate": true,
              "source": "Iran Android App",
              "username_changes": {
                "count": "0"
              }
            },
            "affiliates_highlighted_label": {},
            "avatar": {
              "image_url": "https://pbs.twimg.com/profile_images/2054901638557777920/CUkVwcj7_normal.jpg"
            },
            "core": {
              "created_at": "Thu May 14 07:25:23 +0000 2026",
              "name": "حــ❤ـــب العلـــــــــی(:",
              "screen_name": "ayran_23131"
            },
            "id": "VXNlcjoyMDU0ODI1MzE2NzQxMjU5MjY0",
            "identity_profile_labels_highlighted_label": {},
            "is_blue_verified": false,
            "privacy": {
              "protected": false
            },
            "profile_image_shape": "Circle",
            "rest_id": "2054825316741259264",
            "verification": {
              "verified": false
            },
            "verification_info": {
              "id": "VXNlclZlcmlmaWNhdGlvbkluZm86MjA1NDgyNTMxNjc0MTI1OTI2NA==",
              "is_identity_verified": false
            }
          }
        }
      }
    }
  }
}