{
  "snapshotId": "38a718e4-5aed-4339-9e84-62a9e4be2b89",
  "twitterId": "1942503057058848770",
  "scannedAt": "2026-05-26T22:27:48.714Z",
  "fields": {
    "username": "reza288183",
    "displayName": "reza",
    "profileImageUrl": "https://pbs.twimg.com/profile_images/1942504579322503168/GmPs_D8z_normal.jpg",
    "profileBannerUrl": "",
    "bio": "#ما ملت شهادتیم\n#جانم فدای ایران",
    "selfLocation": "",
    "accountBasedIn": "Iran",
    "connectedVia": "Iran Android App",
    "locatedCountryAccurate": true,
    "verified": false
  },
  "rawPayload": {
    "about_account_query_raw": {
      "data": {
        "user_result_by_screen_name": {
          "id": "VXNlclJlc3VsdHM6MTk0MjUwMzA1NzA1ODg0ODc3MA==",
          "result": {
            "id": "VXNlcjoxOTQyNTAzMDU3MDU4ODQ4Nzcw",
            "core": {
              "name": "reza",
              "created_at": "Tue Jul 08 08:36:43 +0000 2025",
              "screen_name": "reza288183"
            },
            "avatar": {
              "image_url": "https://pbs.twimg.com/profile_images/1942504579322503168/GmPs_D8z_normal.jpg"
            },
            "privacy": {
              "protected": false
            },
            "rest_id": "1942503057058848770",
            "__typename": "User",
            "verification": {
              "verified": false
            },
            "about_profile": {
              "source": "Iran Android App",
              "learn_more_url": "https://help.twitter.com/rules-and-policies/profile-labels",
              "account_based_in": "Iran",
              "username_changes": {
                "count": "0"
              },
              "location_accurate": true,
              "created_country_accurate": true
            },
            "is_blue_verified": false,
            "verification_info": {
              "id": "VXNlclZlcmlmaWNhdGlvbkluZm86MTk0MjUwMzA1NzA1ODg0ODc3MA==",
              "is_identity_verified": false
            },
            "profile_image_shape": "Circle",
            "affiliates_highlighted_label": {},
            "identity_profile_labels_highlighted_label": {}
          }
        }
      }
    },
    "user_by_screen_name_raw": {
      "data": {
        "user": {
          "result": {
            "id": "VXNlcjoxOTQyNTAzMDU3MDU4ODQ4Nzcw",
            "core": {
              "name": "reza",
              "created_at": "Tue Jul 08 08:36:43 +0000 2025",
              "screen_name": "reza288183"
            },
            "avatar": {
              "image_url": "https://pbs.twimg.com/profile_images/1942504579322503168/GmPs_D8z_normal.jpg"
            },
            "legacy": {
              "url": "",
              "entities": {
                "description": {}
              },
              "time_zone": "",
              "utc_offset": 0,
              "description": "#ما ملت شهادتیم\n#جانم فدای ایران",
              "media_count": 1268,
              "listed_count": 0,
              "friends_count": 39,
              "is_translator": false,
              "notifications": false,
              "want_retweets": false,
              "statuses_count": 1309,
              "withheld_scope": "",
              "default_profile": true,
              "followers_count": 57,
              "translator_type": "none",
              "favourites_count": 1454,
              "possibly_sensitive": false,
              "profile_banner_url": "",
              "follow_request_sent": false,
              "fast_followers_count": 0,
              "has_custom_timelines": false,
              "withheld_description": "",
              "default_profile_image": false,
              "normal_followers_count": 57,
              "needs_phone_verification": false,
              "profile_interstitial_type": ""
            },
            "privacy": {
              "protected": false
            },
            "rest_id": "1942503057058848770",
            "location": {
              "location": ""
            },
            "__typename": "User",
            "profile_bio": {
              "description": "#ما ملت شهادتیم\n#جانم فدای ایران"
            },
            "verification": {
              "verified": false
            },
            "dm_permissions": {
              "can_dm": false
            },
            "highlights_info": {
              "highlighted_tweets": "0",
              "can_highlight_tweets": false
            },
            "super_following": false,
            "business_account": {},
            "is_blue_verified": false,
            "media_permissions": {
              "can_media_tag": true
            },
            "super_followed_by": false,
            "verification_info": {
              "is_identity_verified": false
            },
            "follow_request_sent": false,
            "profile_image_shape": "Circle",
            "has_graduated_access": true,
            "profile_sort_enabled": false,
            "super_follow_eligible": false,
            "user_seed_tweet_count": 0,
            "is_profile_translatable": true,
            "legacy_extended_profile": {},
            "premium_gifting_eligible": true,
            "creator_subscriptions_count": 0,
            "parody_commentary_fan_label": "None",
            "affiliates_highlighted_label": {},
            "profile_description_language": "fa",
            "has_hidden_subscriptions_on_profile": false,
            "grok_translated_bio_with_availability": {
              "is_available": false
            }
          }
        }
      }
    }
  }
}