{
  "snapshotId": "6ae0f443-4d87-423a-90a9-4526ea181ef4",
  "twitterId": "1376800266276667399",
  "scannedAt": "2026-05-24T07:43:20.209Z",
  "fields": {
    "username": "Mfazeli114",
    "displayName": "محمد فاضلی",
    "profileImageUrl": "https://pbs.twimg.com/profile_images/1991191198686437376/ZIqGBCbK_normal.jpg",
    "profileBannerUrl": "https://pbs.twimg.com/profile_banners/1376800266276667399/1735585425",
    "bio": "همسر، پدر، دانش‌آموز جامعه‌شناسی و امیدوار به بهبود زندگی ایرانیان.",
    "selfLocation": "Iran, Tehran",
    "accountBasedIn": "Iran",
    "connectedVia": "Iran Android App",
    "locatedCountryAccurate": true,
    "verified": false
  },
  "rawPayload": {
    "about_account_query_raw": {
      "data": {
        "user_result_by_screen_name": {
          "id": "VXNlclJlc3VsdHM6MTM3NjgwMDI2NjI3NjY2NzM5OQ==",
          "result": {
            "id": "VXNlcjoxMzc2ODAwMjY2Mjc2NjY3Mzk5",
            "core": {
              "name": "محمد فاضلی",
              "created_at": "Tue Mar 30 07:36:58 +0000 2021",
              "screen_name": "Mfazeli114"
            },
            "avatar": {
              "image_url": "https://pbs.twimg.com/profile_images/1991191198686437376/ZIqGBCbK_normal.jpg"
            },
            "privacy": {
              "protected": false
            },
            "rest_id": "1376800266276667399",
            "__typename": "User",
            "verification": {
              "verified": false
            },
            "about_profile": {
              "source": "Iran Android App",
              "learn_more_url": "https://help.twitter.com/rules-and-policies/profile-labels",
              "account_based_in": "Iran",
              "username_changes": {
                "count": "1",
                "last_changed_at_msec": "1617090713365"
              },
              "location_accurate": true,
              "created_country_accurate": true
            },
            "is_blue_verified": false,
            "verification_info": {
              "id": "VXNlclZlcmlmaWNhdGlvbkluZm86MTM3NjgwMDI2NjI3NjY2NzM5OQ==",
              "is_identity_verified": false
            },
            "profile_image_shape": "Circle",
            "affiliates_highlighted_label": {},
            "identity_profile_labels_highlighted_label": {}
          }
        }
      }
    },
    "user_by_screen_name_raw": {
      "data": {
        "user": {
          "result": {
            "id": "VXNlcjoxMzc2ODAwMjY2Mjc2NjY3Mzk5",
            "core": {
              "name": "محمد فاضلی",
              "created_at": "Tue Mar 30 07:36:58 +0000 2021",
              "screen_name": "Mfazeli114"
            },
            "avatar": {
              "image_url": "https://pbs.twimg.com/profile_images/1991191198686437376/ZIqGBCbK_normal.jpg"
            },
            "legacy": {
              "url": "https://t.co/oPpGxl9i6i",
              "entities": {
                "url": {
                  "urls": [
                    {
                      "url": "https://t.co/oPpGxl9i6i",
                      "indices": [
                        0,
                        23
                      ],
                      "display_url": "castbox.fm/app/castbox/pl…",
                      "expanded_url": "https://castbox.fm/app/castbox/player/id3687714?v=8.22.11&autoplay=0"
                    }
                  ]
                },
                "description": {}
              },
              "time_zone": "",
              "utc_offset": 0,
              "description": "همسر، پدر، دانش‌آموز جامعه‌شناسی و امیدوار به بهبود زندگی ایرانیان.",
              "media_count": 463,
              "listed_count": 213,
              "friends_count": 419,
              "is_translator": false,
              "notifications": false,
              "want_retweets": false,
              "statuses_count": 5473,
              "withheld_scope": "",
              "default_profile": true,
              "followers_count": 160212,
              "translator_type": "none",
              "favourites_count": 6270,
              "possibly_sensitive": false,
              "profile_banner_url": "https://pbs.twimg.com/profile_banners/1376800266276667399/1735585425",
              "follow_request_sent": false,
              "fast_followers_count": 0,
              "has_custom_timelines": false,
              "pinned_tweet_ids_str": [
                "2026169361216520591"
              ],
              "withheld_description": "",
              "default_profile_image": false,
              "normal_followers_count": 160212,
              "needs_phone_verification": false,
              "profile_interstitial_type": ""
            },
            "privacy": {
              "protected": false
            },
            "rest_id": "1376800266276667399",
            "location": {
              "location": "Iran, Tehran"
            },
            "__typename": "User",
            "profile_bio": {
              "description": "همسر، پدر، دانش‌آموز جامعه‌شناسی و امیدوار به بهبود زندگی ایرانیان."
            },
            "professional": {
              "rest_id": "1522981395844501506",
              "category": [],
              "professional_type": "Creator"
            },
            "verification": {
              "verified": false
            },
            "dm_permissions": {
              "can_dm": false
            },
            "highlights_info": {
              "highlighted_tweets": "0",
              "can_highlight_tweets": false
            },
            "super_following": false,
            "business_account": {},
            "is_blue_verified": false,
            "media_permissions": {
              "can_media_tag": true
            },
            "super_followed_by": false,
            "verification_info": {
              "is_identity_verified": false
            },
            "follow_request_sent": false,
            "profile_image_shape": "Circle",
            "has_graduated_access": true,
            "profile_sort_enabled": true,
            "super_follow_eligible": false,
            "user_seed_tweet_count": 0,
            "is_profile_translatable": true,
            "legacy_extended_profile": {
              "birthdate": {
                "year": 1974,
                "visibility": "MutualFollow",
                "year_visibility": "Public"
              }
            },
            "premium_gifting_eligible": true,
            "creator_subscriptions_count": 0,
            "parody_commentary_fan_label": "None",
            "affiliates_highlighted_label": {},
            "profile_description_language": "fa",
            "has_hidden_subscriptions_on_profile": false,
            "grok_translated_bio_with_availability": {
              "data": {
                "entities": {
                  "urls": [],
                  "symbols": [],
                  "hashtags": [],
                  "user_mentions": []
                },
                "translation": "Husband, father, sociology student, and hopeful for the improvement of Iranians' lives.",
                "source_language": "fa",
                "destination_language": "en"
              },
              "is_available": true
            }
          }
        }
      }
    }
  }
}